[
  {"word": "fabacée", "read": "파바세", "katakana": "ファバセ", "meaning": "콩과 식물"},
	{"word": "fablab", "read": "파블랩", "katakana": "ファブラブ", "meaning": "제작 실험실, 디지털 제작소"},
	{"word": "fable", "read": "파블", "katakana": "ファーブル", "meaning": "우화, 꾸며낸 이야기"},
	{"word": "fabliau", "read": "파블리오", "katakana": "ファブリオ", "meaning": "파블리오(중세 프랑스의 우화시)"},
	{"word": "fablier", "read": "파블리에", "katakana": "ファブリエ", "meaning": "우화집"},
	{"word": "fabricant", "read": "파브리캉", "katakana": "ファブリカン", "meaning": "제조업자, 생산자"},
	{"word": "fabrication", "read": "파브리카시옹", "katakana": "ファブリカシオン", "meaning": "제조, 제작"},
	{"word": "fabrique", "read": "파브리크", "katakana": "ファブリック", "meaning": "공장, 제조소"},
	{"word": "fabriquer", "read": "파브리케", "katakana": "ファブリケ", "meaning": "제조하다, 만들다"},
	{"word": "fabuleux", "read": "파뷜뢰", "katakana": "ファビュルー", "meaning": "전설적인, 엄청난"},
	{"word": "fac", "read": "팍", "katakana": "ファック", "meaning": "대학(학생용 속어)"},
	{"word": "facade", "read": "파사드", "katakana": "ファサード", "meaning": "건물의 정면, 겉모습"},
	{"word": "face", "read": "파스", "katakana": "ファス", "meaning": "얼굴, 표면"},
	{"word": "fâché", "read": "파셰", "katakana": "ファシェ", "meaning": "화난, 성난"},
	{"word": "fâcher", "read": "파셰", "katakana": "ファシェ", "meaning": "화나게 하다, 성나게 하다"},
	{"word": "fâcheux", "read": "파슈", "katakana": "ファシュ", "meaning": "불쾌한, 곤란한"},
	{"word": "facile", "read": "파실", "katakana": "ファシル", "meaning": "쉬운, 용이한"},
	{"word": "facilité", "read": "파실리테", "katakana": "ファシリテ", "meaning": "용이함, 편의"},
	{"word": "faciliter", "read": "파실리테", "katakana": "ファシリテ", "meaning": "쉽게 하다, 용이하게 하다"},
	{"word": "façon", "read": "파송", "katakana": "ファソン", "meaning": "방식, 방법"},
	{"word": "facteur", "read": "팍퇴르", "katakana": "ファクトゥール", "meaning": "요인, 우편배달부"},
	{"word": "factice", "read": "팍티스", "katakana": "ファクティス", "meaning": "인위적인, 가짜의"},
	{"word": "faction", "read": "팍시옹", "katakana": "ファクシオン", "meaning": "파벌, 당파"},
	{"word": "facture", "read": "팍튀르", "katakana": "ファクテュール", "meaning": "청구서, 송장"},
	{"word": "faculté", "read": "파퀼테", "katakana": "ファキュルテ", "meaning": "능력, 학부"},
	{"word": "fade", "read": "파드", "katakana": "ファード", "meaning": "맛없는, 지루한"},
	{"word": "fagot", "read": "파고", "katakana": "ファゴ", "meaning": "장작단, 나뭇단"},
	{"word": "faible", "read": "페블", "katakana": "フェーブル", "meaning": "약한, 힘이 없는"},
	{"word": "faiblesse", "read": "페블레스", "katakana": "フェーブレス", "meaning": "약점, 약함"},
	{"word": "faillir", "read": "파이르", "katakana": "ファイユール", "meaning": "실패하다, 거의 ~할 뻔하다"},
	{"word": "faim", "read": "팡", "katakana": "ファン", "meaning": "배고픔, 굶주림"},
	{"word": "faire", "read": "페르", "katakana": "フェール", "meaning": "하다, 만들다"},
	{"word": "faisan", "read": "페장", "katakana": "フェザン", "meaning": "꿩"},
	{"word": "fait", "read": "페", "katakana": "フェ", "meaning": "사실, 행위"},
	{"word": "faite", "read": "페트", "katakana": "フェット", "meaning": "정상, 꼭대기"},
	{"word": "faîte", "read": "페트", "katakana": "フェット", "meaning": "지붕의 마루"},
	{"word": "faix", "read": "페", "katakana": "フェ", "meaning": "짐, 부담"},
	{"word": "falaise", "read": "팔레즈", "katakana": "ファレーズ", "meaning": "절벽, 해안 절벽"},
	{"word": "falloir", "read": "팔루아르", "katakana": "ファルワール", "meaning": "~해야 한다, 필요하다"},
	{"word": "fameux", "read": "파뫼", "katakana": "ファムー", "meaning": "유명한, 훌륭한"},
	{"word": "familial", "read": "파밀랄", "katakana": "ファミリャル", "meaning": "가족의, 가정의"},
	{"word": "famille", "read": "파미유", "katakana": "ファミユ", "meaning": "가족, 가정"},
	{"word": "famine", "read": "파민", "katakana": "ファミン", "meaning": "기근, 대기근"},
	{"word": "fanatique", "read": "파나티크", "katakana": "ファナティック", "meaning": "광신적인, 열광적인"},
	{"word": "faner", "read": "파네", "katakana": "ファネ", "meaning": "시들다, 바래다"},
	{"word": "fanfare", "read": "팡파르", "katakana": "ファンファール", "meaning": "팡파르, 취주악"},
	{"word": "fantaisie", "read": "팡테지", "katakana": "ファンテジ", "meaning": "공상, 환상"},
	{"word": "fantastique", "read": "팡타스티크", "katakana": "ファンタスティック", "meaning": "환상적인, 놀라운"},
	{"word": "fantôme", "read": "팡톰", "katakana": "ファントーム", "meaning": "유령, 환영"},
	{"word": "farce", "read": "파르스", "katakana": "ファルス", "meaning": "소스, 장난"},
	{"word": "farceur", "read": "파르쇠르", "katakana": "ファルスール", "meaning": "장난꾸러기, 익살꾼"},
	{"word": "fardeau", "read": "파르도", "katakana": "ファルドー", "meaning": "짐, 부담"},
	{"word": "farine", "read": "파린", "katakana": "ファリン", "meaning": "밀가루, 가루"},
	{"word": "farouche", "read": "파루슈", "katakana": "ファルーシュ", "meaning": "겁 많은, 낯을 가리는"},
	{"word": "fascinant", "read": "파시낭", "katakana": "ファシナン", "meaning": "매혹적인, 황홀한"},
	{"word": "fasciner", "read": "파시네", "katakana": "ファシネ", "meaning": "매혹하다, 황홀하게 하다"},
	{"word": "faste", "read": "파스트", "katakana": "ファスト", "meaning": "화려한, 호화로운"},
	{"word": "fat", "read": "파", "katakana": "ファ", "meaning": "거만한, 자만심 많은"},
	{"word": "fatal", "read": "파탈", "katakana": "ファタル", "meaning": "치명적인, 운명적인"},
	{"word": "fatigue", "read": "파티그", "katakana": "ファティーグ", "meaning": "피로, 피곤함"},
	{"word": "fatiguer", "read": "파티게", "katakana": "ファティゲ", "meaning": "피로하게 하다, 지치게 하다"},
	{"word": "fatras", "read": "파트라", "katakana": "ファトラ", "meaning": "잡동사니, 난잡한 것"},
	{"word": "faubourg", "read": "포부르", "katakana": "フォーブール", "meaning": "교외, 외곽"},
	{"word": "faucille", "read": "포시유", "katakana": "フォシーユ", "meaning": "낫"},
	{"word": "faucon", "read": "포콩", "katakana": "フォコン", "meaning": "매, 송골매"},
	{"word": "faudrait", "read": "포드레", "katakana": "フォドレ", "meaning": "~해야 할 것이다"},
	{"word": "faufiler", "read": "포필레", "katakana": "フォフィレ", "meaning": "몰래 들어가다, 살짝 지나가다"},
	{"word": "faune", "read": "폰", "katakana": "フォーヌ", "meaning": "동물군, 동물상"},
	{"word": "fausse", "read": "포스", "katakana": "フォス", "meaning": "거짓의, 가짜의"},
	{"word": "faut", "read": "포", "katakana": "フォ", "meaning": "~해야 한다"},
	{"word": "faute", "read": "포트", "katakana": "フォート", "meaning": "실수, 잘못"},
	{"word": "fauteuil", "read": "포퇴이", "katakana": "フォトゥイユ", "meaning": "안락의자"},
	{"word": "fauve", "read": "포브", "katakana": "フォーヴ", "meaning": "황갈색의, 야생의"},
	{"word": "faux", "read": "포", "katakana": "フォ", "meaning": "거짓의, 가짜의"},
	{"word": "faveur", "read": "파뵈르", "katakana": "ファヴェール", "meaning": "호의, 은총"},
	{"word": "favorable", "read": "파보라블", "katakana": "ファボラブル", "meaning": "유리한, 호의적인"},
	{"word": "favori", "read": "파보리", "katakana": "ファボリ", "meaning": "마음에 드는, 선호하는"},
	{"word": "favoriser", "read": "파보리제", "katakana": "ファボリゼ", "meaning": "돕다, 촉진하다"},
	{"word": "fébrile", "read": "페브릴", "katakana": "フェブリル", "meaning": "열이 있는, 불안한"},
	{"word": "fécond", "read": "페콩", "katakana": "フェコン", "meaning": "비옥한, 다산의"},
	{"word": "féconder", "read": "페콩데", "katakana": "フェコンデ", "meaning": "수정시키다, 비옥하게 하다"},
	{"word": "fécule", "read": "페퀼", "katakana": "フェキュル", "meaning": "녹말, 전분"},
	{"word": "fédéral", "read": "페데랄", "katakana": "フェデラル", "meaning": "연방의, 연합의"},
	{"word": "fédération", "read": "페데라시옹", "katakana": "フェデラシオン", "meaning": "연방, 연합"},
	{"word": "féerique", "read": "페에리크", "katakana": "フェエリック", "meaning": "요정 같은, 마법 같은"},
	{"word": "feindre", "read": "팡드르", "katakana": "ファンドル", "meaning": "가장하다, 꾸며내다"},
	{"word": "feinte", "read": "팡트", "katakana": "ファント", "meaning": "속임수, 위장"},
	{"word": "féliciter", "read": "펠리시테", "katakana": "フェリシテ", "meaning": "축하하다, 칭찬하다"},
	{"word": "félin", "read": "펠랭", "katakana": "フェラン", "meaning": "고양이과의, 고양이 같은"},
	{"word": "femelle", "read": "푸멜", "katakana": "フメル", "meaning": "암컷, 여성"},
	{"word": "féminin", "read": "페미낭", "katakana": "フェミナン", "meaning": "여성의, 여성적인"},
	{"word": "féminisme", "read": "페미니즘", "katakana": "フェミニズム", "meaning": "여성주의, 페미니즘"},
	{"word": "femme", "read": "팜", "katakana": "ファム", "meaning": "여자, 아내"},
	{"word": "fendre", "read": "팡드르", "katakana": "ファンドル", "meaning": "쪼개다, 갈라지다"},
	{"word": "fénelon", "read": "페넬롱", "katakana": "フェネロン", "meaning": "페넬롱(프랑스의 작가)"},
	{"word": "fente", "read": "팡트", "katakana": "ファント", "meaning": "갈라진 틈, 구멍"},
	{"word": "féodal", "read": "페오달", "katakana": "フェオダル", "meaning": "봉건의, 봉건제도의"},
	{"word": "féodalité", "read": "페오달리테", "katakana": "フェオダリテ", "meaning": "봉건제도, 봉건주의"},
	{"word": "fer", "read": "페르", "katakana": "フェール", "meaning": "철, 쇠"},
	{"word": "fer-blanc", "read": "페르블랑", "katakana": "フェールブラン", "meaning": "양철, 백철"},
	{"word": "ferme", "read": "페르므", "katakana": "フェルム", "meaning": "농장, 단단한"},
	{"word": "ferment", "read": "페르망", "katakana": "フェルマン", "meaning": "효모, 발효제"},
	{"word": "fermentation", "read": "페르망타시옹", "katakana": "フェルマンタシオン", "meaning": "발효, 발효작용"},
	{"word": "fermer", "read": "페르메", "katakana": "フェルメ", "meaning": "닫다, 폐쇄하다"},
	{"word": "fermeté", "read": "페르므테", "katakana": "フェルムテ", "meaning": "단단함, 견고함"},
	{"word": "fermeture", "read": "페르므튀르", "katakana": "フェルムテュール", "meaning": "폐쇄, 잠금장치"},
	{"word": "féroce", "read": "페로스", "katakana": "フェロス", "meaning": "야만적인, 잔인한"},
	{"word": "ferraille", "read": "페라이유", "katakana": "フェライユ", "meaning": "고철, 폐철"},
	{"word": "ferrer", "read": "페레", "katakana": "フェレ", "meaning": "말발굽을 달다, 철을 입히다"},
	{"word": "ferronnerie", "read": "페로네리", "katakana": "フェロネリ", "meaning": "철공예, 철제품"},
	{"word": "ferroviaire", "read": "페로비에르", "katakana": "フェロヴィエール", "meaning": "철도의, 철도 관련의"},
	{"word": "ferry", "read": "페리", "katakana": "フェリ", "meaning": "페리, 연락선"},
	{"word": "fertile", "read": "페르틸", "katakana": "フェルティル", "meaning": "비옥한, 다산의"},
	{"word": "fertiliser", "read": "페르틸리제", "katakana": "フェルティリゼ", "meaning": "비옥하게 하다, 비료를 주다"},
	{"word": "ferveur", "read": "페르뵈르", "katakana": "フェルヴェール", "meaning": "열정, 열의"},
	{"word": "fesse", "read": "페스", "katakana": "フェス", "meaning": "엉덩이"},
	{"word": "fessée", "read": "페세", "katakana": "フェセ", "meaning": "엉덩이 때리기"},
	{"word": "fesser", "read": "페세", "katakana": "フェセ", "meaning": "엉덩이를 때리다"},
	{"word": "festin", "read": "페스탕", "katakana": "フェスタン", "meaning": "잔치, 향연"},
	{"word": "festival", "read": "페스티발", "katakana": "フェスティバル", "meaning": "축제, 페스티벌"},
	{"word": "fête", "read": "페트", "katakana": "フェット", "meaning": "축제, 잔치"},
	{"word": "fêter", "read": "페테", "katakana": "フェテ", "meaning": "축하하다, 기념하다"},
	{"word": "feu", "read": "푸", "katakana": "フー", "meaning": "불, 화재"},
	{"word": "feuillage", "read": "푸야주", "katakana": "フヤージュ", "meaning": "잎, 잎사귀"},
	{"word": "feuille", "read": "푸이유", "katakana": "フイユ", "meaning": "잎, 종이"},
	{"word": "feuilleter", "read": "푸이예테", "katakana": "フイエテ", "meaning": "장을 넘기다, 훑어보다"},
	{"word": "feuilleton", "read": "푸이통", "katakana": "フイトン", "meaning": "연속극, 연재소설"},
	{"word": "feutre", "read": "푸트르", "katakana": "フトル", "meaning": "펠트, 펠트펜"},
	{"word": "fève", "read": "페브", "katakana": "フェーヴ", "meaning": "콩, 강낭콩"},
	{"word": "février", "read": "페브리에", "katakana": "フェヴリエ", "meaning": "2월"},
	{"word": "fiabilité", "read": "피아빌리테", "katakana": "フィアビリテ", "meaning": "신뢰성, 신뢰도"},
	{"word": "fiable", "read": "피아블", "katakana": "フィアブル", "meaning": "신뢰할 수 있는, 믿을 수 있는"},
	{"word": "fiacre", "read": "피아크르", "katakana": "フィアクル", "meaning": "마차, 택시 마차"},
	{"word": "fiançailles", "read": "피앙사유", "katakana": "フィアンサイユ", "meaning": "약혼, 약혼식"},
	{"word": "fiancer", "read": "피앙세", "katakana": "フィアンセ", "meaning": "약혼시키다, 약혼하다"},
	{"word": "fiasco", "read": "피아스코", "katakana": "フィアスコ", "meaning": "실패, 대실패"},
	{"word": "fibre", "read": "피브르", "katakana": "フィーブル", "meaning": "섬유, 섬유질"},
	{"word": "fibreux", "read": "피브뢰", "katakana": "フィーブルー", "meaning": "섬유질의, 섬유가 많은"},
	{"word": "ficelle", "read": "피셀", "katakana": "フィセル", "meaning": "끈, 실"},
	{"word": "fiche", "read": "피슈", "katakana": "フィシュ", "meaning": "카드, 표"},
	{"word": "ficher", "read": "피셰", "katakana": "フィシェ", "meaning": "기록하다, 분류하다"},
	{"word": "fichier", "read": "피시에", "katakana": "フィシエ", "meaning": "파일, 문서철"},
	{"word": "fichu", "read": "피슈", "katakana": "フィシュ", "meaning": "망토, 스카프"},
	{"word": "fictif", "read": "피크티프", "katakana": "フィクティフ", "meaning": "가상의, 허구의"},
	{"word": "fiction", "read": "피크시옹", "katakana": "フィクシオン", "meaning": "소설, 허구"},
	{"word": "fidèle", "read": "피델", "katakana": "フィデル", "meaning": "충실한, 신실한"},
	{"word": "fidélité", "read": "피델리테", "katakana": "フィデリテ", "meaning": "충성, 신실함"},
	{"word": "fief", "read": "피에프", "katakana": "フィエフ", "meaning": "영지, 세력권"},
	{"word": "fiel", "read": "피엘", "katakana": "フィエル", "meaning": "쓸개즙, 악의"},
	{"word": "fier", "read": "피에", "katakana": "フィエ", "meaning": "자랑스러운, 거만한"},
	{"word": "fierté", "read": "피에르테", "katakana": "フィエルテ", "meaning": "자부심, 자랑"},
	{"word": "fièvre", "read": "피에브르", "katakana": "フィエーヴル", "meaning": "열, 발열"},
	{"word": "fifre", "read": "피프르", "katakana": "フィフル", "meaning": "피리, 피프"},
	{"word": "figer", "read": "피제", "katakana": "フィジェ", "meaning": "굳어지다, 응고되다"},
	{"word": "figue", "read": "피그", "katakana": "フィーグ", "meaning": "무화과"},
	{"word": "figurant", "read": "피귀랑", "katakana": "フィギュラン", "meaning": "엑스트라, 단역 배우"},
	{"word": "figuratif", "read": "피귀라티프", "katakana": "フィギュラティフ", "meaning": "비유적인, 상징적인"},
	{"word": "figure", "read": "피귀르", "katakana": "フィギュール", "meaning": "모양, 형상"},
	{"word": "figurer", "read": "피귀레", "katakana": "フィギュレ", "meaning": "나타내다, 표현하다"},
	{"word": "fil", "read": "필", "katakana": "フィル", "meaning": "실, 선"},
	{"word": "filament", "read": "필라망", "katakana": "フィラマン", "meaning": "섬유, 필라멘트"},
	{"word": "filature", "read": "필라튀르", "katakana": "フィラテュール", "meaning": "방적, 추적"},
	{"word": "file", "read": "필", "katakana": "フィル", "meaning": "줄, 행렬"},
	{"word": "filer", "read": "필레", "katakana": "フィレ", "meaning": "실을 잣다, 달아나다"},
	{"word": "filet", "read": "필레", "katakana": "フィレ", "meaning": "그물, 필렛"},
	{"word": "filiale", "read": "필리알", "katakana": "フィリアル", "meaning": "자회사, 지사"},
	{"word": "filiation", "read": "필리아시옹", "katakana": "フィリアシオン", "meaning": "계보, 혈통"},
	{"word": "filière", "read": "필리에르", "katakana": "フィリエール", "meaning": "경로, 과정"},
	{"word": "filigrane", "read": "필리그랑", "katakana": "フィリグラン", "meaning": "수채화, 워터마크"},
	{"word": "fille", "read": "피유", "katakana": "フィーユ", "meaning": "소녀, 딸"},
	{"word": "fillette", "read": "피예트", "katakana": "フィエット", "meaning": "어린 소녀"},
	{"word": "film", "read": "필름", "katakana": "フィルム", "meaning": "영화, 필름"},
	{"word": "filmer", "read": "필메", "katakana": "フィルメ", "meaning": "촬영하다, 영화로 만들다"},
	{"word": "filon", "read": "필롱", "katakana": "フィロン", "meaning": "광맥, 좋은 기회"},
	{"word": "fils", "read": "피스", "katakana": "フィス", "meaning": "아들"},
	{"word": "filtre", "read": "필트르", "katakana": "フィルトル", "meaning": "필터, 여과기"},
	{"word": "filtrer", "read": "필트레", "katakana": "フィルトレ", "meaning": "여과하다, 걸러내다"},
	{"word": "fin", "read": "팡", "katakana": "ファン", "meaning": "끝, 종료"},
	{"word": "final", "read": "피날", "katakana": "フィナル", "meaning": "최종의, 마지막의"},
	{"word": "finale", "read": "피날", "katakana": "フィナル", "meaning": "결승전, 피날레"},
	{"word": "finalement", "read": "피날망", "katakana": "フィナルマン", "meaning": "마지막으로, 결국"},
	{"word": "finance", "read": "피낭스", "katakana": "フィナンス", "meaning": "재정, 금융"},
	{"word": "financer", "read": "피낭세", "katakana": "フィナンセ", "meaning": "자금을 제공하다, 재정 지원하다"},
	{"word": "financier", "read": "피낭시에", "katakana": "フィナンシエ", "meaning": "재정의, 금융의"},
	{"word": "finesse", "read": "피네스", "katakana": "フィネス", "meaning": "섬세함, 정교함"},
	{"word": "fini", "read": "피니", "katakana": "フィニ", "meaning": "끝난, 완성된"},
	{"word": "finir", "read": "피니르", "katakana": "フィニール", "meaning": "끝내다, 완성하다"},
	{"word": "finlandais", "read": "팡랑데", "katakana": "ファンランデ", "meaning": "핀란드의, 핀란드어"},
	{"word": "fiole", "read": "피올", "katakana": "フィオル", "meaning": "작은 병, 시험관"},
	{"word": "firme", "read": "피르므", "katakana": "フィルム", "meaning": "회사, 기업"},
	{"word": "fiscal", "read": "피스칼", "katakana": "フィスカル", "meaning": "세금의, 재정의"},
	{"word": "fiscalité", "read": "피스칼리테", "katakana": "フィスカリテ", "meaning": "세제, 조세 제도"},
	{"word": "fissure", "read": "피쉬르", "katakana": "フィシュール", "meaning": "균열, 갈라진 틈"},
	{"word": "fistule", "read": "피스튈", "katakana": "フィステュル", "meaning": "누공, 관"},
	{"word": "fixation", "read": "픽사시옹", "katakana": "フィクサシオン", "meaning": "고정, 부착"},
	{"word": "fixe", "read": "픽스", "katakana": "フィクス", "meaning": "고정된, 불변의"},
	{"word": "fixer", "read": "픽세", "katakana": "フィクセ", "meaning": "고정하다, 정하다"},
	{"word": "fjord", "read": "피오르", "katakana": "フィオール", "meaning": "피오르, 협만"},
	{"word": "flacon", "read": "플라콩", "katakana": "フラコン", "meaning": "작은 병, 플라스크"},
	{"word": "flageller", "read": "플라젤레", "katakana": "フラジェレ", "meaning": "채찍질하다, 매질하다"},
	{"word": "flagrant", "read": "플라그랑", "katakana": "フラグラン", "meaning": "현행의, 명백한"},
	{"word": "flair", "read": "플레르", "katakana": "フレール", "meaning": "후각, 직관"},
	{"word": "flairer", "read": "플레레", "katakana": "フレレ", "meaning": "냄새를 맡다, 감지하다"},
	{"word": "flamand", "read": "플라망", "katakana": "フラマン", "meaning": "플랑드르의, 플랑드르어"},
	{"word": "flambeau", "read": "플랑보", "katakana": "フランボー", "meaning": "횃불, 촛대"},
	{"word": "flamber", "read": "플랑베", "katakana": "フランベ", "meaning": "불을 붙이다, 화염으로 처리하다"},
	{"word": "flamme", "read": "플람", "katakana": "フラム", "meaning": "불꽃, 화염"},
	{"word": "flanc", "read": "플랑", "katakana": "フラン", "meaning": "옆구리, 측면"},
	{"word": "flâner", "read": "플라네", "katakana": "フラネ", "meaning": "거닐다, 산책하다"},
	{"word": "flânerie", "read": "플라네리", "katakana": "フラネリ", "meaning": "산책, 한가로운 시간"},
	{"word": "flanquer", "read": "플랑케", "katakana": "フランケ", "meaning": "던지다, 내던지다"},
	{"word": "flaque", "read": "플라크", "katakana": "フラック", "meaning": "웅덩이, 물웅덩이"},
	{"word": "flash", "read": "플라슈", "katakana": "フラッシュ", "meaning": "플래시, 섬광"},
	{"word": "flatter", "read": "플라테", "katakana": "フラテ", "meaning": "아첨하다, 칭찬하다"},
	{"word": "flatteur", "read": "플라퇴르", "katakana": "フラトゥール", "meaning": "아첨하는, 칭찬하는"},
	{"word": "fléau", "read": "플레오", "katakana": "フレオー", "meaning": "재앙, 곤봉"},
	{"word": "flèche", "read": "플레슈", "katakana": "フレッシュ", "meaning": "화살, 화살표"},
	{"word": "fléchir", "read": "플레시르", "katakana": "フレシール", "meaning": "구부러지다, 굴복하다"},
	{"word": "flétri", "read": "플레트리", "katakana": "フレトリ", "meaning": "시든, 쇠퇴한"},
	{"word": "flétrir", "read": "플레트리르", "katakana": "フレトリール", "meaning": "시들게 하다, 쇠퇴하게 하다"},
	{"word": "fleur", "read": "플뢰르", "katakana": "フルール", "meaning": "꽃, 꽃잎"},
	{"word": "fleurer", "read": "플뢰레", "katakana": "フルレ", "meaning": "향기를 풍기다, 냄새가 나다"},
	{"word": "fleuri", "read": "플뢰리", "katakana": "フルリ", "meaning": "꽃이 핀, 꽃으로 장식된"},
	{"word": "fleurir", "read": "플뢰리르", "katakana": "フルリール", "meaning": "꽃이 피다, 번창하다"},
	{"word": "fleuron", "read": "플뢰롱", "katakana": "フルロン", "meaning": "꽃 모양 장식, 정수"},
	{"word": "fleuve", "read": "플뢰브", "katakana": "フルーヴ", "meaning": "강, 큰 강"},
	{"word": "flexible", "read": "플렉시블", "katakana": "フレクシブル", "meaning": "유연한, 융통성 있는"},
	{"word": "flexion", "read": "플렉시옹", "katakana": "フレクシオン", "meaning": "굴곡, 굴절"},
	{"word": "flirt", "read": "플리르트", "katakana": "フリルト", "meaning": "플러팅, 연애"},
	{"word": "flocon", "read": "플로콩", "katakana": "フロコン", "meaning": "눈송이, 조각"},
	{"word": "floraison", "read": "플로레종", "katakana": "フロレゾン", "meaning": "개화, 번창"},
	{"word": "floral", "read": "플로랄", "katakana": "フロラル", "meaning": "꽃의, 꽃으로 장식된"},
	{"word": "flore", "read": "플로르", "katakana": "フロール", "meaning": "식물상, 식물군"},
	{"word": "florissant", "read": "플로리상", "katakana": "フロリサン", "meaning": "번창하는, 융성한"},
	{"word": "flot", "read": "플로", "katakana": "フロ", "meaning": "물결, 흐름"},
	{"word": "flottant", "read": "플로탕", "katakana": "フロタン", "meaning": "떠 있는, 불확실한"},
	{"word": "flotte", "read": "플로트", "katakana": "フロット", "meaning": "함대, 선단"},
	{"word": "flotter", "read": "플로테", "katakana": "フロテ", "meaning": "떠다니다, 흔들리다"},
	{"word": "flou", "read": "플루", "katakana": "フルー", "meaning": "흐릿한, 모호한"},
	{"word": "fluctuation", "read": "플뤽튀아시옹", "katakana": "フリュクテュアシオン", "meaning": "변동, 요동"},
	{"word": "fluctuer", "read": "플뤽튀에", "katakana": "フリュクテュエ", "meaning": "변동하다, 요동치다"},
	{"word": "fluide", "read": "플뤼드", "katakana": "フリュード", "meaning": "유체, 액체"},
	{"word": "fluidité", "read": "플뤼디테", "katakana": "フリュディテ", "meaning": "유동성, 흐름"},
	{"word": "fluor", "read": "플뤼오르", "katakana": "フリュオール", "meaning": "플루오르, 불소"},
	{"word": "flux", "read": "플뤼", "katakana": "フリュ", "meaning": "흐름, 유입"},
	{"word": "focal", "read": "포칼", "katakana": "フォカル", "meaning": "초점의, 중심의"},
	{"word": "focaliser", "read": "포칼리제", "katakana": "フォカリゼ", "meaning": "초점을 맞추다, 집중하다"},
	{"word": "foi", "read": "푸아", "katakana": "フォア", "meaning": "신앙, 믿음"},
	{"word": "foie", "read": "푸아", "katakana": "フォア", "meaning": "간, 간장"},
	{"word": "foin", "read": "푸앵", "katakana": "フォアン", "meaning": "건초, 마른 풀"},
	{"word": "foire", "read": "푸아르", "katakana": "フォアール", "meaning": "박람회, 시장"},
	{"word": "fois", "read": "푸아", "katakana": "フォア", "meaning": "번, 회"},
	{"word": "foison", "read": "푸아종", "katakana": "フォアゾン", "meaning": "풍부함, 다량"},
	{"word": "foisonner", "read": "푸아소네", "katakana": "フォアソネ", "meaning": "풍부하다, 넘치다"},
	{"word": "fol", "read": "폴", "katakana": "フォル", "meaning": "미친, 광기 어린"},
	{"word": "folâtrer", "read": "폴라트레", "katakana": "フォラトレ", "meaning": "장난치다, 놀다"},
  {"word": "folie", "read": "폴리", "katakana": "フォリ", "meaning": "광기, 미치광이"},
	{"word": "folklore", "read": "폴클로르", "katakana": "フォルクロール", "meaning": "민속, 민속학"},
	{"word": "folle", "read": "폴", "katakana": "フォル", "meaning": "미친 여자, 광녀"},
	{"word": "follet", "read": "폴레", "katakana": "フォレ", "meaning": "장난스러운, 변덕스러운"},
	{"word": "follicule", "read": "폴리퀼", "katakana": "フォリキュル", "meaning": "모낭, 여포"},
	{"word": "fomenter", "read": "포망테", "katakana": "フォマンテ", "meaning": "선동하다, 부추기다"},
	{"word": "foncé", "read": "퐁세", "katakana": "フォンセ", "meaning": "진한, 어두운"},
	{"word": "foncer", "read": "퐁세", "katakana": "フォンセ", "meaning": "돌진하다, 돌격하다"},
	{"word": "fonction", "read": "퐁크시옹", "katakana": "フォンクシオン", "meaning": "기능, 작용"},
	{"word": "fonctionnaire", "read": "퐁크시오네르", "katakana": "フォンクシオネール", "meaning": "공무원, 관리"},
	{"word": "fonctionnel", "read": "퐁크시오넬", "katakana": "フォンクシオネル", "meaning": "기능적인, 작동하는"},
	{"word": "fonctionner", "read": "퐁크시오네", "katakana": "フォンクシオネ", "meaning": "작동하다, 기능하다"},
	{"word": "fond", "read": "퐁", "katakana": "フォン", "meaning": "바닥, 기반"},
	{"word": "fondamental", "read": "퐁다멍탈", "katakana": "フォンダマンタル", "meaning": "근본적인, 기본적인"},
	{"word": "fondation", "read": "퐁다시옹", "katakana": "フォンダシオン", "meaning": "기초, 재단"},
	{"word": "fonder", "read": "퐁데", "katakana": "フォンデ", "meaning": "설립하다, 창립하다"},
	{"word": "fonderie", "read": "퐁드리", "katakana": "フォンドリ", "meaning": "주조소, 제철소"},
	{"word": "fondre", "read": "퐁드르", "katakana": "フォンドル", "meaning": "녹다, 용해되다"},
	{"word": "fonds", "read": "퐁", "katakana": "フォン", "meaning": "자금, 기금"},
	{"word": "fontaine", "read": "퐁텐", "katakana": "フォンテン", "meaning": "분수, 샘"},
	{"word": "fonte", "read": "퐁트", "katakana": "フォント", "meaning": "주조, 용해"},
	{"word": "football", "read": "푸트볼", "katakana": "フットボール", "meaning": "축구"},
	{"word": "for", "read": "포르", "katakana": "フォール", "meaning": "숲, 삼림"},
	{"word": "forage", "read": "포라주", "katakana": "フォラージュ", "meaning": "시추, 굴착"},
	{"word": "forain", "read": "포랭", "katakana": "フォラン", "meaning": "이동식의, 순회하는"},
	{"word": "forban", "read": "포르방", "katakana": "フォルバン", "meaning": "해적, 악당"},
	{"word": "forçat", "read": "포르사", "katakana": "フォルサ", "meaning": "강제 노동자, 죄수"},
	{"word": "force", "read": "포르스", "katakana": "フォルス", "meaning": "힘, 강도"},
	{"word": "forcené", "read": "포르스네", "katakana": "フォルスネ", "meaning": "광기 어린, 미친"},
	{"word": "forcer", "read": "포르세", "katakana": "フォルセ", "meaning": "강요하다, 강제하다"},
	{"word": "forcément", "read": "포르세망", "katakana": "フォルセマン", "meaning": "반드시, 필연적으로"},
	{"word": "forer", "read": "포레", "katakana": "フォレ", "meaning": "시추하다, 구멍을 뚫다"},
	{"word": "forestier", "read": "포레스티에", "katakana": "フォレスティエ", "meaning": "삼림의, 산림의"},
	{"word": "forêt", "read": "포레", "katakana": "フォレ", "meaning": "숲, 삼림"},
	{"word": "forfait", "read": "포르페", "katakana": "フォルフェ", "meaning": "포기, 기권"},
	{"word": "forfaiture", "read": "포르페튀르", "katakana": "フォルフェテュール", "meaning": "직무유기, 배신"},
	{"word": "forge", "read": "포르주", "katakana": "フォルジュ", "meaning": "대장간, 제철소"},
	{"word": "forger", "read": "포르제", "katakana": "フォルジェ", "meaning": "단조하다, 만들다"},
	{"word": "forgeron", "read": "포르주롱", "katakana": "フォルジュロン", "meaning": "대장장이"},
	{"word": "formaliser", "read": "포르말리제", "katakana": "フォルマリゼ", "meaning": "공식화하다, 형식화하다"},
	{"word": "formalité", "read": "포르말리테", "katakana": "フォルマリテ", "meaning": "형식, 절차"},
	{"word": "format", "read": "포르마", "katakana": "フォルマ", "meaning": "형식, 크기"},
	{"word": "formation", "read": "포르마시옹", "katakana": "フォルマシオン", "meaning": "형성, 교육"},
	{"word": "forme", "read": "포르므", "katakana": "フォルム", "meaning": "형태, 모양"},
	{"word": "formel", "read": "포르멜", "katakana": "フォルメル", "meaning": "형식적인, 명시적인"},
	{"word": "former", "read": "포르메", "katakana": "フォルメ", "meaning": "형성하다, 교육하다"},
	{"word": "formidable", "read": "포르미다블", "katakana": "フォルミダブル", "meaning": "훌륭한, 대단한"},
	{"word": "formule", "read": "포르뮬", "katakana": "フォルミュール", "meaning": "공식, 수식"},
	{"word": "formuler", "read": "포르뮬레", "katakana": "フォルミュレ", "meaning": "공식화하다, 표현하다"},
	{"word": "fornication", "read": "포르니카시옹", "katakana": "フォルニカシオン", "meaning": "음란, 간음"},
	{"word": "fort", "read": "포르", "katakana": "フォール", "meaning": "강한, 강력한"},
	{"word": "forte", "read": "포르트", "katakana": "フォルト", "meaning": "강한, 큰"},
	{"word": "fortement", "read": "포르트망", "katakana": "フォルトマン", "meaning": "강하게, 크게"},
	{"word": "forteresse", "read": "포르테레스", "katakana": "フォルテレス", "meaning": "요새, 성채"},
	{"word": "fortification", "read": "포르티피카시옹", "katakana": "フォルティフィカシオン", "meaning": "요새화, 방어시설"},
	{"word": "fortifier", "read": "포르티피에", "katakana": "フォルティフィエ", "meaning": "강화하다, 요새화하다"},
	{"word": "fortin", "read": "포르탕", "katakana": "フォルタン", "meaning": "작은 요새, 초소"},
	{"word": "fortiori", "read": "포르시오리", "katakana": "フォルシオリ", "meaning": "더욱 더, 하물며"},
	{"word": "fortuit", "read": "포르튀이", "katakana": "フォルテュイ", "meaning": "우연한, 우발적인"},
	{"word": "fortune", "read": "포르튀느", "katakana": "フォルテュヌ", "meaning": "운명, 재산"},
	{"word": "forum", "read": "포륨", "katakana": "フォリュム", "meaning": "포럼, 토론장"},
	{"word": "fosse", "read": "포스", "katakana": "フォス", "meaning": "구덩이, 웅덩이"},
	{"word": "fossé", "read": "포세", "katakana": "フォセ", "meaning": "도랑, 해자"},
	{"word": "fossile", "read": "포실", "katakana": "フォシル", "meaning": "화석, 고풍스러운"},
	{"word": "fossiliser", "read": "포실리제", "katakana": "フォシリゼ", "meaning": "화석화하다, 경직되다"},
	{"word": "fou", "read": "푸", "katakana": "フー", "meaning": "미친, 광기 어린"},
	{"word": "foudre", "read": "푸드르", "katakana": "フードル", "meaning": "번개, 벼락"},
	{"word": "fouet", "read": "푸에", "katakana": "フエ", "meaning": "채찍, 채찍질"},
	{"word": "fouetter", "read": "푸에테", "katakana": "フエテ", "meaning": "채찍질하다, 휘젓다"},
	{"word": "fougue", "read": "푸그", "katakana": "フゴ", "meaning": "열정, 기세"},
	{"word": "fougueux", "read": "푸그", "katakana": "フゴ", "meaning": "열정적인, 기세 좋은"},
	{"word": "fouille", "read": "푸이유", "katakana": "フイユ", "meaning": "발굴, 수색"},
	{"word": "fouiller", "read": "푸이예", "katakana": "フイエ", "meaning": "발굴하다, 수색하다"},
	{"word": "fouillis", "read": "푸이", "katakana": "フイ", "meaning": "혼란, 뒤죽박죽"},
	{"word": "foulard", "read": "푸라르", "katakana": "フラール", "meaning": "스카프, 넥타이"},
	{"word": "foule", "read": "푸르", "katakana": "フール", "meaning": "군중, 대중"},
	{"word": "fouler", "read": "푸레", "katakana": "フレ", "meaning": "밟다, 짓밟다"},
	{"word": "four", "read": "푸르", "katakana": "フール", "meaning": "화덕, 오븐"},
	{"word": "fourbe", "read": "푸르브", "katakana": "フールブ", "meaning": "교활한, 간사한"},
	{"word": "fourberie", "read": "푸르브리", "katakana": "フールブリ", "meaning": "교활함, 간사함"},
	{"word": "fourbi", "read": "푸르비", "katakana": "フールビ", "meaning": "잡동사니, 장비"},
	{"word": "fourche", "read": "푸르슈", "katakana": "フールシュ", "meaning": "쇠스랑, 갈래"},
	{"word": "fourchette", "read": "푸르셰트", "katakana": "フールシェット", "meaning": "포크, 식사용 포크"},
	{"word": "fourgon", "read": "푸르공", "katakana": "フールゴン", "meaning": "화물차, 짐차"},
	{"word": "fourmi", "read": "푸르미", "katakana": "フールミ", "meaning": "개미"},
	{"word": "fournaise", "read": "푸르네즈", "katakana": "フールネーズ", "meaning": "용광로, 불지옥"},
	{"word": "fourneau", "read": "푸르노", "katakana": "フールノー", "meaning": "화덕, 난로"},
	{"word": "fournir", "read": "푸르니르", "katakana": "フールニール", "meaning": "공급하다, 제공하다"},
	{"word": "fourniture", "read": "푸르니튀르", "katakana": "フールニテュール", "meaning": "공급, 비품"},
	{"word": "fourrage", "read": "푸라주", "katakana": "フラージュ", "meaning": "사료, 건초"},
	{"word": "fourreau", "read": "푸로", "katakana": "フロー", "meaning": "집, 덮개"},
	{"word": "fourrer", "read": "푸레", "katakana": "フレ", "meaning": "넣다, 채우다"},
	{"word": "fourrure", "read": "푸뤼르", "katakana": "フリュール", "meaning": "모피, 털가죽"},
	{"word": "fourvoyer", "read": "푸르부아예", "katakana": "フールヴォワエ", "meaning": "길을 잃게 하다, 잘못 인도하다"},
	{"word": "foutaise", "read": "푸테즈", "katakana": "フテーズ", "meaning": "허튼소리, 어리석은 말"},
	{"word": "foutre", "read": "푸트르", "katakana": "フトル", "meaning": "넣다, 던지다"},
	{"word": "foutriquet", "read": "푸트리케", "katakana": "フトリケ", "meaning": "하찮은 사람, 보잘것없는 사람"},
	{"word": "foyer", "read": "푸아예", "katakana": "フォワイエ", "meaning": "화로, 가정"},
	{"word": "fracas", "read": "프라카", "katakana": "フラカ", "meaning": "요란한 소리, 파열음"},
	{"word": "fraction", "read": "프락시옹", "katakana": "フラクシオン", "meaning": "분수, 부분"},
	{"word": "fractionner", "read": "프락시오네", "katakana": "フラクシオネ", "meaning": "분할하다, 나누다"},
	{"word": "fracture", "read": "프락튀르", "katakana": "フラクテュール", "meaning": "골절, 파열"},
	{"word": "fracturer", "read": "프락튀레", "katakana": "フラクテュレ", "meaning": "골절시키다, 파열시키다"},
	{"word": "fragile", "read": "프라질", "katakana": "フラジル", "meaning": "연약한, 깨지기 쉬운"},
	{"word": "fragilité", "read": "프라질리테", "katakana": "フラジリテ", "meaning": "연약함, 취약성"},
	{"word": "fragment", "read": "프라그망", "katakana": "フラグマン", "meaning": "파편, 조각"},
	{"word": "fragmenter", "read": "프라그망테", "katakana": "フラグマンテ", "meaning": "파편화하다, 분할하다"},
	{"word": "fraîche", "read": "프레슈", "katakana": "フレッシュ", "meaning": "신선한, 시원한"},
	{"word": "fraîcheur", "read": "프레슈르", "katakana": "フレッシュール", "meaning": "신선함, 시원함"},
	{"word": "frais", "read": "프레", "katakana": "フレ", "meaning": "신선한, 비용"},
	{"word": "fraise", "read": "프레즈", "katakana": "フレーズ", "meaning": "딸기, 프릴"},
	{"word": "framboise", "read": "프랑부아즈", "katakana": "フランボワーズ", "meaning": "라즈베리, 산딸기"},
	{"word": "franc", "read": "프랑", "katakana": "フラン", "meaning": "솔직한, 프랑(화폐)"},
	{"word": "français", "read": "프랑세", "katakana": "フランセ", "meaning": "프랑스의, 프랑스어"},
	{"word": "franchir", "read": "프랑시르", "katakana": "フランシール", "meaning": "넘다, 통과하다"},
	{"word": "franchise", "read": "프랑시즈", "katakana": "フランシーズ", "meaning": "면제, 특권"},
	{"word": "franciscain", "read": "프랑시스캥", "katakana": "フランシスカン", "meaning": "프란체스코회의"},
	{"word": "franc-maçon", "read": "프랑마송", "katakana": "フランマソン", "meaning": "프리메이슨, 공동체 회원"},
	{"word": "franc-maçonnerie", "read": "프랑마소네리", "katakana": "フランマソネリ", "meaning": "프리메이슨, 공동체"},
	{"word": "franc-parler", "read": "프랑파를레", "katakana": "フランパルレ", "meaning": "솔직한 말, 거침없는 말"},
	{"word": "franc-tireur", "read": "프랑티뢰르", "katakana": "フランティルール", "meaning": "유격대원, 자유사수"},
	{"word": "frange", "read": "프랑주", "katakana": "フランジュ", "meaning": "가장자리, 프린지"},
	{"word": "frangin", "read": "프랑장", "katakana": "フランジャン", "meaning": "형, 동생(속어)"},
	{"word": "frangine", "read": "프랑진", "katakana": "フランジーヌ", "meaning": "언니, 누나(속어)"},
	{"word": "frappant", "read": "프라팡", "katakana": "フラパン", "meaning": "인상적인, 놀라운"},
	{"word": "frapper", "read": "프라페", "katakana": "フラペ", "meaning": "치다, 두드리다"},
	{"word": "fraternel", "read": "프라테르넬", "katakana": "フラテルネル", "meaning": "형제의, 우애로운"},
	{"word": "fraterniser", "read": "프라테르니제", "katakana": "フラテルニゼ", "meaning": "우애를 나누다, 친교를 맺다"},
	{"word": "fraternité", "read": "프라테르니테", "katakana": "フラテルニテ", "meaning": "우애, 형제애"},
	{"word": "fratricide", "read": "프라트리시드", "katakana": "フラトリシード", "meaning": "형제 살해, 형제 살해자"},
	{"word": "fraude", "read": "프로드", "katakana": "フロード", "meaning": "사기, 부정"},
	{"word": "frauder", "read": "프로데", "katakana": "フロデ", "meaning": "사기치다, 부정하다"},
	{"word": "frayer", "read": "프레예", "katakana": "フレイエ", "meaning": "길을 내다, 터를 닦다"},
	{"word": "frayeur", "read": "프레예르", "katakana": "フレイエール", "meaning": "공포, 두려움"},
	{"word": "fredaine", "read": "프르덴", "katakana": "フルデン", "meaning": "장난, 장난스러운 행동"},
	{"word": "fredonner", "read": "프르도네", "katakana": "フルドネ", "meaning": "흥얼거리다, 콧노래를 부르다"},
	{"word": "free-lance", "read": "프리랑스", "katakana": "フリーランス", "meaning": "프리랜서, 자유계약자"},
	{"word": "frein", "read": "프랭", "katakana": "フラン", "meaning": "제동장치, 브레이크"},
	{"word": "freiner", "read": "프레네", "katakana": "フレネ", "meaning": "제동하다, 억제하다"},
	{"word": "frelater", "read": "프를라테", "katakana": "フルラテ", "meaning": "불순물을 섞다, 위조하다"},
	{"word": "frelon", "read": "프를롱", "katakana": "フルロン", "meaning": "말벌, 큰 말벌"},
	{"word": "frémir", "read": "프레미르", "katakana": "フレミール", "meaning": "떨다, 전율하다"},
	{"word": "frêne", "read": "프렌", "katakana": "フレン", "meaning": "물푸레나무"},
	{"word": "frénésie", "read": "프레네지", "katakana": "フレネジ", "meaning": "광기, 열광"},
	{"word": "frénétique", "read": "프레네티크", "katakana": "フレネティック", "meaning": "광기 어린, 열광적인"},
	{"word": "fréquemment", "read": "프레캉망", "katakana": "フレカンマン", "meaning": "자주, 빈번하게"},
	{"word": "fréquence", "read": "프레캉스", "katakana": "フレカンス", "meaning": "빈도, 주파수"},
	{"word": "fréquent", "read": "프레캉", "katakana": "フレカン", "meaning": "빈번한, 자주 있는"},
	{"word": "fréquenter", "read": "프레캉테", "katakana": "フレカンテ", "meaning": "자주 가다, 교제하다"},
	{"word": "frère", "read": "프레르", "katakana": "フレール", "meaning": "형제, 동료"},
	{"word": "frêle", "read": "프렐", "katakana": "フレル", "meaning": "연약한, 약한"},
	{"word": "frémir", "read": "프레미르", "katakana": "フレミール", "meaning": "떨다, 전율하다"},
	{"word": "frénésie", "read": "프레네지", "katakana": "フレネジ", "meaning": "광기, 열광"},
	{"word": "frénétique", "read": "프레네티크", "katakana": "フレネティック", "meaning": "광기 어린, 열광적인"},
	{"word": "fréquemment", "read": "프레캉망", "katakana": "フレカンマン", "meaning": "자주, 빈번하게"},
	{"word": "fréquence", "read": "프레캉스", "katakana": "フレカンス", "meaning": "빈도, 주파수"},
	{"word": "fréquent", "read": "프레캉", "katakana": "フレカン", "meaning": "빈번한, 자주 있는"},
	{"word": "fréquenter", "read": "프레캉테", "katakana": "フレカンテ", "meaning": "자주 가다, 교제하다"},
	{"word": "frère", "read": "프레르", "katakana": "フレール", "meaning": "형제, 동료"},
	{"word": "frêle", "read": "프렐", "katakana": "フレル", "meaning": "연약한, 약한"},
  {"word": "frémir", "read": "프레미르", "katakana": "フレミール", "meaning": "떨다, 전율하다"},
	{"word": "frénésie", "read": "프레네지", "katakana": "フレネジ", "meaning": "광기, 열광"},
	{"word": "frénétique", "read": "프레네티크", "katakana": "フレネティック", "meaning": "광기 어린, 열광적인"},
	{"word": "fréquemment", "read": "프레캉망", "katakana": "フレカンマン", "meaning": "자주, 빈번하게"},
	{"word": "fréquence", "read": "프레캉스", "katakana": "フレカンス", "meaning": "빈도, 주파수"},
	{"word": "fréquent", "read": "프레캉", "katakana": "フレカン", "meaning": "빈번한, 자주 있는"},
	{"word": "fréquenter", "read": "프레캉테", "katakana": "フレカンテ", "meaning": "자주 가다, 교제하다"},
	{"word": "frère", "read": "프레르", "katakana": "フレール", "meaning": "형제, 동료"},
	{"word": "frêle", "read": "프렐", "katakana": "フレル", "meaning": "연약한, 약한"},
	{"word": "fresque", "read": "프레스크", "katakana": "フレスク", "meaning": "프레스코화, 벽화"},
	{"word": "fret", "read": "프레", "katakana": "フレ", "meaning": "화물, 운임"},
	{"word": "frêter", "read": "프레테", "katakana": "フレテ", "meaning": "선박을 용선하다, 배를 빌리다"},
	{"word": "fretin", "read": "프르탕", "katakana": "フルタン", "meaning": "작은 물고기, 하찮은 것"},
	{"word": "friche", "read": "프리슈", "katakana": "フリシュ", "meaning": "황무지, 방치된 땅"},
	{"word": "fricot", "read": "프리코", "katakana": "フリコ", "meaning": "요리, 음식"},
	{"word": "friction", "read": "프릭시옹", "katakana": "フリクシオン", "meaning": "마찰, 문지름"},
	{"word": "frictionner", "read": "프릭시오네", "katakana": "フリクシオネ", "meaning": "문지르다, 마찰하다"},
	{"word": "frigide", "read": "프리지드", "katakana": "フリジード", "meaning": "냉담한, 성욕이 없는"},
	{"word": "frigorifier", "read": "프리고리피에", "katakana": "フリゴリフィエ", "meaning": "냉장하다, 냉각하다"},
	{"word": "frileux", "read": "프릴뢰", "katakana": "フリルー", "meaning": "추위를 타는, 소심한"},
	{"word": "frime", "read": "프림", "katakana": "フリム", "meaning": "허세, 과시"},
	{"word": "frimer", "read": "프리메", "katakana": "フリメ", "meaning": "허세를 부리다, 과시하다"},
	{"word": "frimousse", "read": "프리무스", "katakana": "フリムス", "meaning": "귀여운 얼굴, 얼굴"},
	{"word": "fringale", "read": "프랭갈", "katakana": "フランガル", "meaning": "갑작스러운 배고픔, 식욕"},
	{"word": "fringant", "read": "프랭강", "katakana": "フランガン", "meaning": "활발한, 생기있는"},
	{"word": "fringue", "read": "프랭그", "katakana": "フラング", "meaning": "옷, 의복(속어)"},
	{"word": "friper", "read": "프리페", "katakana": "フリペ", "meaning": "구겨지게 하다, 낡게 하다"},
	{"word": "friperie", "read": "프리프리", "katakana": "フリプリ", "meaning": "헌옷 가게, 낡은 물건"},
	{"word": "fripon", "read": "프리퐁", "katakana": "フリポン", "meaning": "장난꾸러기, 장난스러운"},
	{"word": "friponnerie", "read": "프리포네리", "katakana": "フリポネリ", "meaning": "장난, 장난스러운 행동"},
	{"word": "frire", "read": "프리르", "katakana": "フリール", "meaning": "튀기다, 볶다"},
	{"word": "friser", "read": "프리제", "katakana": "フリゼ", "meaning": "곱슬곱슬하게 하다, 거의 닿다"},
	{"word": "frisette", "read": "프리제트", "katakana": "フリゼット", "meaning": "작은 곱슬, 곱슬머리"},
	{"word": "frisottis", "read": "프리조티", "katakana": "フリゾティ", "meaning": "작은 곱슬, 곱슬머리"},
	{"word": "frisson", "read": "프리송", "katakana": "フリソン", "meaning": "전율, 떨림"},
	{"word": "frissonner", "read": "프리소네", "katakana": "フリソネ", "meaning": "떨다, 전율하다"},
	{"word": "frit", "read": "프리", "katakana": "フリ", "meaning": "튀긴, 끝난"},
	{"word": "frite", "read": "프리트", "katakana": "フリット", "meaning": "감자튀김, 튀긴 것"},
	{"word": "friture", "read": "프리튀르", "katakana": "フリテュール", "meaning": "튀김, 튀긴 음식"},
	{"word": "frivole", "read": "프리볼", "katakana": "フリボル", "meaning": "경박한, 하찮은"},
	{"word": "froc", "read": "프로크", "katakana": "フロック", "meaning": "수도복, 가운"},
	{"word": "froid", "read": "프르와", "katakana": "フルワ", "meaning": "추운, 차가운"},
	{"word": "froideur", "read": "프르와되르", "katakana": "フルワドゥール", "meaning": "냉담함, 차가움"},
	{"word": "froissement", "read": "프르와스망", "katakana": "フルワスマン", "meaning": "구겨짐, 마찰"},
	{"word": "froisser", "read": "프르와세", "katakana": "フルワセ", "meaning": "구겨지게 하다, 상처주다"},
	{"word": "frôler", "read": "프롤레", "katakana": "フロレ", "meaning": "스치다, 간신히 피하다"},
	{"word": "fromage", "read": "프로마주", "katakana": "フロマージュ", "meaning": "치즈, 치즈 제품"},
	{"word": "froment", "read": "프로망", "katakana": "フロマン", "meaning": "밀, 밀가루"},
	{"word": "froncer", "read": "프롱세", "katakana": "フロンセ", "meaning": "주름을 잡다, 찌푸리다"},
	{"word": "fronde", "read": "프롱드", "katakana": "フロンド", "meaning": "새총, 투석기"},
	{"word": "front", "read": "프롱", "katakana": "フロン", "meaning": "이마, 전면"},
	{"word": "frontière", "read": "프롱티에르", "katakana": "フロンティエール", "meaning": "국경, 경계"},
	{"word": "fronton", "read": "프롱통", "katakana": "フロントン", "meaning": "박공, 정면"},
	{"word": "frotter", "read": "프로테", "katakana": "フロテ", "meaning": "문지르다, 닦다"},
	{"word": "frottis", "read": "프로티", "katakana": "フロティ", "meaning": "문지른 자국, 스케치"},
	{"word": "froufrou", "read": "프루프루", "katakana": "フルフル", "meaning": "바스락거리는 소리, 화려한 장식"},
	{"word": "fructifier", "read": "프뤽티피에", "katakana": "フリュクティフィエ", "meaning": "열매를 맺다, 이익을 내다"},
	{"word": "fructueux", "read": "프뤽튀", "katakana": "フリュクテュ", "meaning": "수익성 있는, 유익한"},
	{"word": "frugal", "read": "프뤼갈", "katakana": "フリュガル", "meaning": "검소한, 절제된"},
	{"word": "frugalité", "read": "프뤼갈리테", "katakana": "フリュガリテ", "meaning": "검소함, 절제"},
	{"word": "fruit", "read": "프뤼이", "katakana": "フリュイ", "meaning": "과일, 열매"},
	{"word": "fruiterie", "read": "프뤼이트리", "katakana": "フリュイトリ", "meaning": "과일 가게, 과일 상점"},
	{"word": "fruits", "read": "프뤼이", "katakana": "フリュイ", "meaning": "과일들, 열매들"},
	{"word": "fruste", "read": "프뤼스트", "katakana": "フリュスト", "meaning": "거친, 세련되지 않은"},
	{"word": "frustrer", "read": "프뤼스트레", "katakana": "フリュストレ", "meaning": "좌절시키다, 실망시키다"},
	{"word": "fuchsia", "read": "퓌크시아", "katakana": "フュクシア", "meaning": "푸크시아, 자주색"},
	{"word": "fuel", "read": "퓌엘", "katakana": "フュエル", "meaning": "연료, 석유"},
	{"word": "fugace", "read": "퓌가스", "katakana": "フュガス", "meaning": "덧없는, 일시적인"},
	{"word": "fugitif", "read": "퓌지티프", "katakana": "フュジティフ", "meaning": "도망자, 일시적인"},
	{"word": "fugue", "read": "퓌그", "katakana": "フュグ", "meaning": "도망, 푸가"},
	{"word": "fuir", "read": "퓌이르", "katakana": "フュイール", "meaning": "도망치다, 피하다"},
	{"word": "fuite", "read": "퓌이트", "katakana": "フュイット", "meaning": "도망, 누수"},
	{"word": "fulgurant", "read": "퓌르귀랑", "katakana": "フュルギュラン", "meaning": "번개 같은, 급격한"},
	{"word": "fulminer", "read": "퓌르미네", "katakana": "フュルミネ", "meaning": "격노하다, 폭발하다"},
	{"word": "fumée", "read": "퓌메", "katakana": "フュメ", "meaning": "연기, 흄"},
	{"word": "fumer", "read": "퓌메", "katakana": "フュメ", "meaning": "연기를 피우다, 흡연하다"},
	{"word": "fumet", "read": "퓌메", "katakana": "フュメ", "meaning": "향기, 냄새"},
	{"word": "fumier", "read": "퓌미에", "katakana": "フュミエ", "meaning": "거름, 비료"},
	{"word": "fumigène", "read": "퓌미젠", "katakana": "フュミジェン", "meaning": "연막, 연기 발생기"},
	{"word": "fumiste", "read": "퓌미스트", "katakana": "フュミスト", "meaning": "연통공, 사기꾼"},
	{"word": "fumoir", "read": "퓌무아르", "katakana": "フュムワール", "meaning": "훈제실, 흡연실"},
	{"word": "funèbre", "read": "퓌네브르", "katakana": "フュネーブル", "meaning": "장례의, 비극적인"},
	{"word": "funérailles", "read": "퓌네라유", "katakana": "フュネライユ", "meaning": "장례식, 장례"},
	{"word": "funéraire", "read": "퓌네레르", "katakana": "フュネレール", "meaning": "장례의, 장묘의"},
	{"word": "funeste", "read": "퓌네스트", "katakana": "フュネスト", "meaning": "불행한, 치명적인"},
	{"word": "fur", "read": "퓌르", "katakana": "フュール", "meaning": "털, 모피"},
	{"word": "fureur", "read": "퓌뢰르", "katakana": "フュルール", "meaning": "분노, 광기"},
	{"word": "furibond", "read": "퓌리봉", "katakana": "フリボン", "meaning": "격노한, 광분한"},
	{"word": "furie", "read": "퓌리", "katakana": "フリ", "meaning": "분노, 광기"},
	{"word": "furieux", "read": "퓌리", "katakana": "フリ", "meaning": "격노한, 광분한"},
	{"word": "furoncle", "read": "퓌롱클", "katakana": "フロンクル", "meaning": "종기, 종창"},
	{"word": "furtif", "read": "퓌르티프", "katakana": "フュルティフ", "meaning": "몰래하는, 은밀한"},
	{"word": "fusain", "read": "퓌쟁", "katakana": "フザン", "meaning": "목탄, 스케치"},
	{"word": "fusée", "read": "퓌제", "katakana": "フゼ", "meaning": "로켓, 폭죽"},
	{"word": "fuselage", "read": "퓌즐라주", "katakana": "フズラージュ", "meaning": "동체, 기체"},
	{"word": "fusil", "read": "퓌지", "katakana": "フジ", "meaning": "총, 라이플"},
	{"word": "fusiller", "read": "퓌지예", "katakana": "フジエ", "meaning": "총살하다, 사형하다"},
	{"word": "fusion", "read": "퓌지옹", "katakana": "フジオン", "meaning": "융합, 합병"},
	{"word": "fusionner", "read": "퓌지오네", "katakana": "フジオネ", "meaning": "융합하다, 합병하다"},
	{"word": "fustiger", "read": "퓌스티제", "katakana": "フスティジェ", "meaning": "비난하다, 질책하다"},
	{"word": "fût", "read": "퓌", "katakana": "フュ", "meaning": "통, 기둥"},
	{"word": "futaille", "read": "퓌타유", "katakana": "フタイユ", "meaning": "통, 나무통"},
	{"word": "futile", "read": "퓌틸", "katakana": "フティル", "meaning": "하찮은, 시시한"},
	{"word": "futur", "read": "퓌튀르", "katakana": "フテュール", "meaning": "미래의, 장래의"},
	{"word": "futuriste", "read": "퓌튀리스트", "katakana": "フテュリスト", "meaning": "미래파의, 미래주의자"},
	{"word": "fuyard", "read": "퓌이아르", "katakana": "フイヤール", "meaning": "도망자, 탈주자"},
	{"word": "fuyez", "read": "퓌이예", "katakana": "フイエ", "meaning": "도망치세요, 피하세요"},
	{"word": "fuyons", "read": "퓌이용", "katakana": "フイヨン", "meaning": "도망치자, 피하자"}
]